{
  "resourceType": "ValueSet",
  "id": "match-method",
  "text": {
    "status": "generated",
    "div": "<div xmlns=\"http://www.w3.org/1999/xhtml\"><ul><li>Include all codes defined in <a href=\"CodeSystem-match-method.html\"><code>http://ibm.com/fhir/cdm/CodeSystem/match-method</code></a></li></ul></div>"
  },
  "url": "http://ibm.com/fhir/cdm/ValueSet/match-method",
  "version": "7.0.0",
  "name": "MatchMethodValueSet",
  "title": "Match Method Value Set",
  "status": "active",
  "date": "2022-09-07T15:39:45+00:00",
  "publisher": "Alvearie Team",
  "description": "Codes indicating methods used to identify matched entities",
  "jurisdiction": [
    {
      "coding": [
        {
          "system": "urn:iso:std:iso:3166",
          "code": "US"
        }
      ]
    }
  ],
  "compose": {
    "include": [
      {
        "system": "http://ibm.com/fhir/cdm/CodeSystem/match-method"
      }
    ]
  }
}