{
  "resourceType": "ValueSet",
  "id": "ncpdp-dispense-as-written",
  "text": {
    "status": "generated",
    "div": "<div xmlns=\"http://www.w3.org/1999/xhtml\"><ul><li>Include all codes defined in <a href=\"CodeSystem-ncpdp-dispense-as-written.html\"><code>http://ibm.com/fhir/cdm/CodeSystem/ncpdp-dispense-as-written</code></a></li></ul></div>"
  },
  "url": "http://ibm.com/fhir/cdm/ValueSet/ncpdp-dispense-as-written",
  "version": "6.1.1",
  "name": "NCPDPDispenseAsWrittenValueSet",
  "title": "NCPDP Dispense As Written Value Set",
  "status": "active",
  "date": "2022-06-06T15:56:40+00:00",
  "publisher": "Alvearie Team",
  "description": "The NCPDP industry standard description of how the product was dispensed.",
  "jurisdiction": [
    {
      "coding": [
        {
          "system": "urn:iso:std:iso:3166",
          "code": "US"
        }
      ]
    }
  ],
  "compose": {
    "include": [
      {
        "system": "http://ibm.com/fhir/cdm/CodeSystem/ncpdp-dispense-as-written"
      }
    ]
  }
}